[
  {
    "name": "cee",
    "value": "2a5bu1%2F4PuAv%2FflE63LRhjFz6N%2BZVesp4U4plIMsoAI%3D.%7B%7D",
    "domain": ".mpc-prod-11-s6uit34pua-uc.a.run.app",
    "path": "/events/a4071c33b3eae60f95bee48a159190c7bfc5ac459df4ec4d0efd0eecdd2f5744",
    "expires": 1769092630.669173,
    "httpOnly": true,
    "secure": true,
    "sameSite": "None"
  },
  {
    "name": "vid_rt",
    "value": "eyJhbGciOiJIUzI1NiIsInR5cCI6IkpXVCJ9.eyJzdWIiOiIxZmFiZTliYS02MDE5LTQ1M2MtYjcwYS0zOTUxZmY0MmRiMjMiLCJzZXNzIjoiYzcyNTI4NjMtYjFkOS00ZjgyLWI5MTctM2I5OGEzZWQ1NmYwIiwiaWF0IjoxNzYxMzE2NjI3LCJleHAiOjE3NjM5MDg2MjcsImlzcyI6InZpZCJ9.r1qbFFPTf5HuBl1OF45tfWNXlKp1R_fYD8zJWj4pHts",
    "domain": ".www.chedraui.com.mx",
    "path": "/api/vtexid/refreshtoken/webstore",
    "expires": 1763908627.02331,
    "httpOnly": true,
    "secure": true,
    "sameSite": "Strict"
  },
  {
    "name": "_csrf",
    "value": "MNzXFxSvbEPYnFJ5ngLA-rra",
    "domain": "chedraui-prod.us.auth0.com",
    "path": "/usernamepassword/login",
    "expires": 1762180612.332672,
    "httpOnly": true,
    "secure": true,
    "sameSite": "Lax"
  },
  {
    "name": "_li_ss",
    "value": "CggKBgiiARCFHA",
    "domain": "i.liadm.com",
    "path": "/s",
    "expires": 1763908611.588988,
    "httpOnly": false,
    "secure": true,
    "sameSite": "None"
  },
  {
    "name": "VtexWorkspace",
    "value": "master%3A-",
    "domain": "www.chedraui.com.mx",
    "path": "/",
    "expires": 1761402961,
    "httpOnly": false,
    "secure": true,
    "sameSite": "None"
  },
  {
    "name": "VtexRCSessionIdv7",
    "value": "76db72fd-05db-40f0-8ff5-2225c1fdf79b",
    "domain": ".chedraui.com.mx",
    "path": "/",
    "expires": 1761318431,
    "httpOnly": false,
    "secure": false,
    "sameSite": "Lax"
  },
  {
    "name": "VtexRCMacIdv7",
    "value": "4bb2a67b-e662-4e9a-a9d8-3a4cf15705a8",
    "domain": ".chedraui.com.mx",
    "path": "/",
    "expires": 1792852631,
    "httpOnly": false,
    "secure": false,
    "sameSite": "Lax"
  },
  {
    "name": "vtex-search-session",
    "value": "effdb32e66394f81aa0728fd856d2cc0",
    "domain": ".chedraui.com.mx",
    "path": "/",
    "expires": 1761318428.136441,
    "httpOnly": false,
    "secure": false,
    "sameSite": "Lax"
  },
  {
    "name": "vtex-search-anonymous",
    "value": "9210859880f2405fb24bd4b0ad51975e",
    "domain": ".chedraui.com.mx",
    "path": "/",
    "expires": 1792852628.136769,
    "httpOnly": false,
    "secure": false,
    "sameSite": "Lax"
  },
  {
    "name": "sp-variant",
    "value": "66844d747af2d50d0f2e2357-variantNull",
    "domain": ".chedraui.com.mx",
    "path": "/",
    "expires": 1761318428.136182,
    "httpOnly": false,
    "secure": false,
    "sameSite": "Lax"
  },
  {
    "name": "checkout.vtex.com",
    "value": "__ofid=d026560ce53d4ebbb37181cf087089a3",
    "domain": ".www.chedraui.com.mx",
    "path": "/",
    "expires": 1776868629.674225,
    "httpOnly": true,
    "secure": true,
    "sameSite": "Lax"
  },
  {
    "name": "GRV_BHV_IDCC5577",
    "value": "3",
    "domain": ".groovinads.com",
    "path": "/",
    "expires": 1765204631.286746,
    "httpOnly": false,
    "secure": true,
    "sameSite": "None"
  },
  {
    "name": "GRV_BHV_SKU5577",
    "value": "undefined",
    "domain": ".groovinads.com",
    "path": "/",
    "expires": 1765204631.286814,
    "httpOnly": false,
    "secure": true,
    "sameSite": "None"
  },
  {
    "name": "GRV_BHV_IDVAR5577",
    "value": "3",
    "domain": ".groovinads.com",
    "path": "/",
    "expires": 1765204631.286861,
    "httpOnly": false,
    "secure": true,
    "sameSite": "None"
  },
  {
    "name": "GRV_BHV_DATE5577",
    "value": "2025-10-24",
    "domain": ".groovinads.com",
    "path": "/",
    "expires": 1763908631.286914,
    "httpOnly": false,
    "secure": true,
    "sameSite": "None"
  },
  {
    "name": "GRV_IDU",
    "value": "ce710a4f2d3a703",
    "domain": ".groovinads.com",
    "path": "/",
    "expires": 1787236631.286959,
    "httpOnly": false,
    "secure": true,
    "sameSite": "None"
  },
  {
    "name": "GRV_BHV_BRND_5577",
    "value": "Disabled",
    "domain": ".groovinads.com",
    "path": "/",
    "expires": 1761338207.81435,
    "httpOnly": false,
    "secure": true,
    "sameSite": "None"
  },
  {
    "name": "_TargetOne_ShortLivedCookie",
    "value": "YDBCQUYPCXR85RLNFNUS1761316608001",
    "domain": "www.chedraui.com.mx",
    "path": "/",
    "expires": 1761318428,
    "httpOnly": false,
    "secure": false,
    "sameSite": "Lax"
  },
  {
    "name": "_TargetOne_Session_Cookie_start_time",
    "value": "2025-10-24 14:36:48.002 UTC",
    "domain": "www.chedraui.com.mx",
    "path": "/",
    "expires": 1761318428,
    "httpOnly": false,
    "secure": false,
    "sameSite": "Lax"
  },
  {
    "name": "_gcl_au",
    "value": "1.1.631009006.1761316608",
    "domain": ".chedraui.com.mx",
    "path": "/",
    "expires": 1769092608,
    "httpOnly": false,
    "secure": false,
    "sameSite": "Lax"
  },
  {
    "name": "uid",
    "value": "be82d4b7-2565-4f54-a593-dec5012041c6",
    "domain": ".criteo.com",
    "path": "/",
    "expires": 1795012608.132708,
    "httpOnly": false,
    "secure": true,
    "sameSite": "None"
  },
  {
    "name": "_ttp",
    "value": "34W5hlx2zCbBGp7TlawhSa5vhiB",
    "domain": ".tiktok.com",
    "path": "/",
    "expires": 1795012628.528955,
    "httpOnly": false,
    "secure": true,
    "sameSite": "None"
  },
  {
    "name": "muidn",
    "value": "p9oMXPfNVzA7",
    "domain": ".mgid.com",
    "path": "/",
    "expires": 1792852631.377479,
    "httpOnly": false,
    "secure": true,
    "sameSite": "None"
  },
  {
    "name": "mg_sync",
    "value": "{\"834131\":1761316608}",
    "domain": "cm.mgid.com",
    "path": "/",
    "expires": 1763908631.37762,
    "httpOnly": false,
    "secure": true,
    "sameSite": "None"
  },
  {
    "name": "g",
    "value": "OhGSx2qJVjaH3Eh104nn_1761316609462",
    "domain": ".creativecdn.com",
    "path": "/",
    "expires": 1792852609.254534,
    "httpOnly": false,
    "secure": true,
    "sameSite": "None"
  },
  {
    "name": "c",
    "value": "OhGSx2qJVjaH3Eh104nn_23LKb0xojl6IVrjPposI_1761316609462",
    "domain": ".creativecdn.com",
    "path": "/",
    "expires": 1792852609.254611,
    "httpOnly": false,
    "secure": true,
    "sameSite": "None",
    "partitionKey": "https://chedraui.com.mx",
    "_crHasCrossSiteAncestor": true
  },
  {
    "name": "ts",
    "value": "1761316609",
    "domain": ".creativecdn.com",
    "path": "/",
    "expires": 1792852609.254637,
    "httpOnly": false,
    "secure": true,
    "sameSite": "None",
    "partitionKey": "https://chedraui.com.mx",
    "_crHasCrossSiteAncestor": true
  },
  {
    "name": "_ga",
    "value": "GA1.1.903360213.1761316609",
    "domain": ".chedraui.com.mx",
    "path": "/",
    "expires": 1795876609.427116,
    "httpOnly": false,
    "secure": false,
    "sameSite": "Lax"
  },
  {
    "name": "_tt_enable_cookie",
    "value": "1",
    "domain": ".chedraui.com.mx",
    "path": "/",
    "expires": 1795012630,
    "httpOnly": false,
    "secure": false,
    "sameSite": "Lax"
  },
  {
    "name": "_ttp",
    "value": "01K8BAD7JS3Z260SY21V9RCKYG_.tt.2",
    "domain": ".chedraui.com.mx",
    "path": "/",
    "expires": 1795012630,
    "httpOnly": false,
    "secure": false,
    "sameSite": "Lax"
  },
  {
    "name": "t_gid",
    "value": "71540056-7ed3-453e-807f-914018e3d540-tuctff51481",
    "domain": ".taboola.com",
    "path": "/",
    "expires": 1792852631.39638,
    "httpOnly": false,
    "secure": true,
    "sameSite": "None"
  },
  {
    "name": "t_pt_gid",
    "value": "71540056-7ed3-453e-807f-914018e3d540-tuctff51481",
    "domain": ".taboola.com",
    "path": "/",
    "expires": 1792852631.396619,
    "httpOnly": false,
    "secure": true,
    "sameSite": "None",
    "partitionKey": "https://chedraui.com.mx",
    "_crHasCrossSiteAncestor": true
  },
  {
    "name": "smc_ls_session",
    "value": "1761316609649",
    "domain": ".chedraui.com.mx",
    "path": "/",
    "expires": -1,
    "httpOnly": false,
    "secure": false,
    "sameSite": "Lax"
  },
  {
    "name": "ar_debug",
    "value": "1",
    "domain": "measurement-api.criteo.com",
    "path": "/",
    "expires": -1,
    "httpOnly": true,
    "secure": true,
    "sameSite": "None"
  },
  {
    "name": "XANDR_PANID",
    "value": "YzSltdoEsYbNTlD7udYnKD21Sy-a7Jqha9HX-uprtlYM03Ia3obn89bBcnUYsK3i4L24eUZtYic5HLssACbJluhag3_G1XjUA5Ez0P1ZBEc.",
    "domain": ".adnxs.com",
    "path": "/",
    "expires": 1769092611.487529,
    "httpOnly": false,
    "secure": true,
    "sameSite": "None",
    "partitionKey": "https://chedraui.com.mx",
    "_crHasCrossSiteAncestor": true
  },
  {
    "name": "uuid2",
    "value": "3169543980697087421",
    "domain": ".adnxs.com",
    "path": "/",
    "expires": 1769092611.48764,
    "httpOnly": true,
    "secure": true,
    "sameSite": "None"
  },
  {
    "name": "MUID",
    "value": "1A6D00B5522A69A2306E163A53496858",
    "domain": ".bing.com",
    "path": "/",
    "expires": 1795012611.256493,
    "httpOnly": false,
    "secure": true,
    "sameSite": "None"
  },
  {
    "name": "MR",
    "value": "0",
    "domain": ".bat.bing.com",
    "path": "/",
    "expires": 1761921411.224473,
    "httpOnly": false,
    "secure": true,
    "sameSite": "None"
  },
  {
    "name": "_fbp",
    "value": "fb.2.1761316610252.408653532884095212",
    "domain": ".chedraui.com.mx",
    "path": "/",
    "expires": 1769092630,
    "httpOnly": false,
    "secure": false,
    "sameSite": "Lax"
  },
  {
    "name": "IDE",
    "value": "AHWqTUnYzgz5kc2vcBqpstG_TxyqFGHHVBGR6yZ7L5Sq2jnUI9ib3kjmb_D6TzNReh8",
    "domain": ".doubleclick.net",
    "path": "/",
    "expires": 1795876610.28609,
    "httpOnly": true,
    "secure": true,
    "sameSite": "None"
  },
  {
    "name": "receive-cookie-deprecation",
    "value": "1",
    "domain": ".doubleclick.net",
    "path": "/",
    "expires": 1776868631.199117,
    "httpOnly": true,
    "secure": true,
    "sameSite": "None",
    "partitionKey": "https://chedraui.com.mx",
    "_crHasCrossSiteAncestor": true
  },
  {
    "name": "__zlcmid",
    "value": "1UHo0tamDK7cBjg",
    "domain": ".chedraui.com.mx",
    "path": "/",
    "expires": 1792852630,
    "httpOnly": false,
    "secure": false,
    "sameSite": "Lax"
  },
  {
    "name": "MR",
    "value": "0",
    "domain": ".c.bing.com",
    "path": "/",
    "expires": 1761921411.256577,
    "httpOnly": false,
    "secure": true,
    "sameSite": "None"
  },
  {
    "name": "visitor-id",
    "value": "4043182115509701000V10",
    "domain": ".media.net",
    "path": "/",
    "expires": 1792852611.310157,
    "httpOnly": false,
    "secure": true,
    "sameSite": "None"
  },
  {
    "name": "data-c",
    "value": "k-Xbn4P6C5qF6KqjLplW5li41AvCYyiGTEvPSkzw~~3",
    "domain": ".media.net",
    "path": "/",
    "expires": 1763908611.310229,
    "httpOnly": false,
    "secure": true,
    "sameSite": "None"
  },
  {
    "name": "data-c-ts",
    "value": "1761316611",
    "domain": ".media.net",
    "path": "/",
    "expires": 1763908611.310251,
    "httpOnly": false,
    "secure": true,
    "sameSite": "None"
  },
  {
    "name": "CMID",
    "value": "aPuPA8AoIeoAAb0xAlbCzgAA",
    "domain": ".casalemedia.com",
    "path": "/",
    "expires": 1792852611.453934,
    "httpOnly": false,
    "secure": true,
    "sameSite": "None"
  },
  {
    "name": "CMPS",
    "value": "4201",
    "domain": ".casalemedia.com",
    "path": "/",
    "expires": 1769092611.324867,
    "httpOnly": false,
    "secure": true,
    "sameSite": "None"
  },
  {
    "name": "CMPRO",
    "value": "4201",
    "domain": ".casalemedia.com",
    "path": "/",
    "expires": 1769092611.454006,
    "httpOnly": false,
    "secure": true,
    "sameSite": "None"
  },
  {
    "name": "tuuid",
    "value": "019450b4-00b4-4d3e-9eb0-cd76a0c148bc",
    "domain": ".360yield.com",
    "path": "/",
    "expires": 1769092611.34653,
    "httpOnly": true,
    "secure": true,
    "sameSite": "None"
  },
  {
    "name": "tuuid_lu",
    "value": "1761316611",
    "domain": ".360yield.com",
    "path": "/",
    "expires": 1769092611.346659,
    "httpOnly": true,
    "secure": true,
    "sameSite": "None"
  },
  {
    "name": "um",
    "value": "!38,MJKRqTA97iy2TKg.o.Hl5eT7lmY-Crwvrqk2R4aR2K-9nFnf8Ek1bL361ihqiNMhIpEt4cA7BJB.OFN.s8sSYkw8xX4,1769092611",
    "domain": ".360yield.com",
    "path": "/",
    "expires": 1769092611.389701,
    "httpOnly": true,
    "secure": true,
    "sameSite": "None"
  },
  {
    "name": "umeh",
    "value": "!38,0,1823524611,-1",
    "domain": ".360yield.com",
    "path": "/",
    "expires": 1769092611.389813,
    "httpOnly": true,
    "secure": true,
    "sameSite": "None"
  },
  {
    "name": "mv_tokens",
    "value": "%7B%22mv_uuid%22%3A%22e13c7dd0-b0e6-11f0-aa53-975aca29a1e8%22%2C%22version%22%3A%22invalidate-verizon-pushes%22%7D",
    "domain": "exchange.mediavine.com",
    "path": "/",
    "expires": 1762526211.428941,
    "httpOnly": false,
    "secure": true,
    "sameSite": "None"
  },
  {
    "name": "mv_tokens_invalidate-verizon-pushes",
    "value": "%7B%22mv_uuid%22%3A%22e13c7dd0-b0e6-11f0-aa53-975aca29a1e8%22%2C%22version%22%3A%22invalidate-verizon-pushes%22%7D",
    "domain": "exchange.mediavine.com",
    "path": "/",
    "expires": 1762526211.429008,
    "httpOnly": false,
    "secure": true,
    "sameSite": "None"
  },
  {
    "name": "am_tokens",
    "value": "%7B%22mv_uuid%22%3A%22e13c7dd0-b0e6-11f0-aa53-975aca29a1e8%22%2C%22version%22%3A%22invalidate-verizon-pushes%22%7D",
    "domain": "exchange.mediavine.com",
    "path": "/",
    "expires": 1762526211.429027,
    "httpOnly": false,
    "secure": true,
    "sameSite": "None"
  },
  {
    "name": "am_tokens_invalidate-verizon-pushes",
    "value": "%7B%22mv_uuid%22%3A%22e13c7dd0-b0e6-11f0-aa53-975aca29a1e8%22%2C%22version%22%3A%22invalidate-verizon-pushes%22%7D",
    "domain": "exchange.mediavine.com",
    "path": "/",
    "expires": 1762526211.429045,
    "httpOnly": false,
    "secure": true,
    "sameSite": "None"
  },
  {
    "name": "criteo",
    "value": "%7B%22id%22%3A%22k-egaEVqC5qF6KqjLplW5li41AvCafbC5KljvuEg%22%2C%22version%22%3A%22criteo%22%7D",
    "domain": "exchange.mediavine.com",
    "path": "/",
    "expires": 1762526211.429071,
    "httpOnly": false,
    "secure": true,
    "sameSite": "None"
  },
  {
    "name": "tuuid",
    "value": "c2af2215-9b42-4ba4-a70a-7ecc8ca3e9a2",
    "domain": ".bidswitch.net",
    "path": "/",
    "expires": 1792852611.517472,
    "httpOnly": false,
    "secure": true,
    "sameSite": "None"
  },
  {
    "name": "c",
    "value": "1761316611",
    "domain": ".bidswitch.net",
    "path": "/",
    "expires": 1792852611.439279,
    "httpOnly": false,
    "secure": true,
    "sameSite": "None"
  },
  {
    "name": "tuuid_lu",
    "value": "1761316611",
    "domain": ".bidswitch.net",
    "path": "/",
    "expires": 1792852611.517549,
    "httpOnly": false,
    "secure": true,
    "sameSite": "None"
  },
  {
    "name": "visitor",
    "value": "926d95ec-5de0-4cfe-8f64-629c64e394f8",
    "domain": ".postrelease.com",
    "path": "/",
    "expires": 1792852611.479327,
    "httpOnly": false,
    "secure": true,
    "sameSite": "None"
  },
  {
    "name": "status",
    "value": "0",
    "domain": ".postrelease.com",
    "path": "/",
    "expires": 1792852611.479438,
    "httpOnly": false,
    "secure": true,
    "sameSite": "None"
  },
  {
    "name": "UID",
    "value": "3fa9a54cfd5c6137dca9df194c2ba0",
    "domain": ".ads.stickyadstv.com",
    "path": "/",
    "expires": 1763908611.485469,
    "httpOnly": false,
    "secure": true,
    "sameSite": "None"
  },
  {
    "name": "anj",
    "value": "dTM7k!M40*dWIy(ghqdmU(5<MhckQp!A#FA(<h!ysZtz`T^=hA6:3d74hf9tdZRpu2PEJ`b0swblYRs./1kBG3`HaRkM1p'0haFriX@+YmVmkf(j'kU-$Z]HBX5?/Z)2II02UvIOq4Q_OnuWG6X9mvV6r_OEc6rLc:#P?P:)CY@XxW3(>JUk(Md+>)fy)q$?2GI",
    "domain": ".adnxs.com",
    "path": "/",
    "expires": 1769092611.487605,
    "httpOnly": true,
    "secure": true,
    "sameSite": "None"
  },
  {
    "name": "lidid",
    "value": "a4dd1e32-be62-40a5-aa65-a7ff0949853f",
    "domain": ".liadm.com",
    "path": "/",
    "expires": 1795876611.589072,
    "httpOnly": false,
    "secure": true,
    "sameSite": "None"
  },
  {
    "name": "demdex",
    "value": "52303941497218208123593352678489512736",
    "domain": ".demdex.net",
    "path": "/",
    "expires": 1776868611.66133,
    "httpOnly": false,
    "secure": true,
    "sameSite": "None"
  },
  {
    "name": "tt_viewer",
    "value": "a1b30361-1cb8-4375-b103-b015f912058d",
    "domain": ".teads.tv",
    "path": "/",
    "expires": 1792766211.604221,
    "httpOnly": false,
    "secure": true,
    "sameSite": "None"
  },
  {
    "name": "v1_151",
    "value": "1",
    "domain": ".revcontent.com",
    "path": "/",
    "expires": 1763908611.621202,
    "httpOnly": false,
    "secure": true,
    "sameSite": "None"
  },
  {
    "name": "v2_151",
    "value": "k-oXHiwaC5qF6KqjLplW5li41AvCYjdioHW3sJIg",
    "domain": ".revcontent.com",
    "path": "/",
    "expires": 1763908611.621265,
    "httpOnly": false,
    "secure": true,
    "sameSite": "None"
  },
  {
    "name": "pid",
    "value": "8314236832416615441",
    "domain": ".smartadserver.com",
    "path": "/",
    "expires": 1769092611.660402,
    "httpOnly": false,
    "secure": true,
    "sameSite": "None"
  },
  {
    "name": "TestIfCookieP",
    "value": "ok",
    "domain": ".smartadserver.com",
    "path": "/",
    "expires": 1795531011.660478,
    "httpOnly": false,
    "secure": true,
    "sameSite": "None"
  },
  {
    "name": "csync",
    "value": "79:k-v2gR4aC5qF6KqjLplW5li41AvCbWATnm6PSsNQ",
    "domain": ".smartadserver.com",
    "path": "/",
    "expires": 1763908611.660501,
    "httpOnly": false,
    "secure": true,
    "sameSite": "None"
  },
  {
    "name": "dpm",
    "value": "52303941497218208123593352678489512736",
    "domain": ".dpm.demdex.net",
    "path": "/",
    "expires": 1776868611.66139,
    "httpOnly": false,
    "secure": true,
    "sameSite": "None"
  },
  {
    "name": "tvid",
    "value": "194834a661ac49f6bc742f9e0998254e",
    "domain": ".tremorhub.com",
    "path": "/",
    "expires": 1792873511.728801,
    "httpOnly": false,
    "secure": true,
    "sameSite": "None"
  },
  {
    "name": "tv_UICR",
    "value": "k-fCD1CKC5qF6KqjLplW5li41AvCZPM7oya_8qqA",
    "domain": ".tremorhub.com",
    "path": "/",
    "expires": 1763908611.728906,
    "httpOnly": false,
    "secure": true,
    "sameSite": "None"
  },
  {
    "name": "audit_p",
    "value": "1|kQblIEstiOyPp8fQm81kyFfYQUxHlyhGBFqVcaT32Kc/f76a5RWklO4MkFI3JIHez5HJ/1QosNcwHTRO1/p4iCck1N7K9KkV0dqlR5NoluSCD9zFQIvrTaFpynmvyIcUT5hM/qV1vdLC/c3O6KT6O5hoFKmWzIcWQ8HNO0m+gvR16h2LKXkYaJDy+KCnXKr4N6JXMcYuiJM=",
    "domain": ".rubiconproject.com",
    "path": "/",
    "expires": 1792852611.753732,
    "httpOnly": false,
    "secure": true,
    "sameSite": "None",
    "partitionKey": "https://chedraui.com.mx",
    "_crHasCrossSiteAncestor": true
  },
  {
    "name": "khaos",
    "value": "MH4YFNN0-1N-M7LO",
    "domain": ".rubiconproject.com",
    "path": "/",
    "expires": 1792852611.753828,
    "httpOnly": false,
    "secure": true,
    "sameSite": "None"
  },
  {
    "name": "khaos_p",
    "value": "MH4YFNN0-1N-M7LO",
    "domain": ".rubiconproject.com",
    "path": "/",
    "expires": 1792852611.753854,
    "httpOnly": false,
    "secure": true,
    "sameSite": "None",
    "partitionKey": "https://chedraui.com.mx",
    "_crHasCrossSiteAncestor": true
  },
  {
    "name": "audit",
    "value": "1|kQblIEstiOyPp8fQm81kyFfYQUxHlyhGBFqVcaT32Kc/f76a5RWklO4MkFI3JIHez5HJ/1QosNcwHTRO1/p4iCck1N7K9KkV0dqlR5NoluSCD9zFQIvrTaFpynmvyIcUT5hM/qV1vdLC/c3O6KT6O5hoFKmWzIcWQ8HNO0m+gvR16h2LKXkYaJDy+KCnXKr4N6JXMcYuiJM=",
    "domain": ".rubiconproject.com",
    "path": "/",
    "expires": 1792852611.753879,
    "httpOnly": false,
    "secure": true,
    "sameSite": "None"
  },
  {
    "name": "receive-cookie-deprecation",
    "value": "1",
    "domain": ".rubiconproject.com",
    "path": "/",
    "expires": 1769092611.753898,
    "httpOnly": true,
    "secure": true,
    "sameSite": "None",
    "partitionKey": "https://chedraui.com.mx",
    "_crHasCrossSiteAncestor": true
  },
  {
    "name": "_rxuuid",
    "value": "%7B%22rx_uuid%22%3A%22RX-5d48f0be-1a44-4f80-bda2-4684a23a7335-005%22%7D",
    "domain": ".1rx.io",
    "path": "/",
    "expires": 1792852611.765059,
    "httpOnly": true,
    "secure": true,
    "sameSite": "None"
  },
  {
    "name": "tluidp",
    "value": "1716386942617910898185",
    "domain": ".3lift.com",
    "path": "/",
    "expires": 1769092611.844644,
    "httpOnly": false,
    "secure": true,
    "sameSite": "None",
    "partitionKey": "https://chedraui.com.mx",
    "_crHasCrossSiteAncestor": true
  },
  {
    "name": "tluid",
    "value": "1716386942617910898185",
    "domain": ".3lift.com",
    "path": "/",
    "expires": 1769092611.845007,
    "httpOnly": false,
    "secure": true,
    "sameSite": "None"
  },
  {
    "name": "_uid",
    "value": "umo198d_7565994513588479950",
    "domain": ".fwmrm.net",
    "path": "/",
    "expires": 1776868612.219749,
    "httpOnly": false,
    "secure": true,
    "sameSite": "None"
  },
  {
    "name": "zync-uuid",
    "value": "5063eeb8-f40e-4af0-8f6c-7e1d96d82e20:1761316612.0089664",
    "domain": ".rezync.com",
    "path": "/",
    "expires": 1795012612.147267,
    "httpOnly": false,
    "secure": true,
    "sameSite": "None"
  },
  {
    "name": "dsp_43",
    "value": "ERID@@",
    "domain": ".user-sync.fwmrm.net",
    "path": "/",
    "expires": 1766500611.865572,
    "httpOnly": false,
    "secure": true,
    "sameSite": "None"
  },
  {
    "name": "_rxuuid",
    "value": "%7B%22rx_uuid%22%3A%22RX-5d48f0be-1a44-4f80-bda2-4684a23a7335-005%22%7D",
    "domain": ".targeting.unrulymedia.com",
    "path": "/",
    "expires": 1792852612.028744,
    "httpOnly": true,
    "secure": true,
    "sameSite": "None"
  },
  {
    "name": "eud",
    "value": "H4sIAAAAAAAA_1XIsRWAMAgFwAmsMgc-IOSHuI0aGMjS0kktfZZ3V-mNUSMOpzQOsj2ZPHFSD5kD0zWUN-mQKoDoyuwDsLssX6rZ83d7Ab_CChlaAAAA",
    "domain": ".rfihub.com",
    "path": "/",
    "expires": 1795012612.046285,
    "httpOnly": false,
    "secure": true,
    "sameSite": "None"
  },
  {
    "name": "ruds",
    "value": "H4sIAAAAAAAA_-MSsjS3MDE3NzExMzAwMzUyMjA1FuIz1E1OjvT1scjOiyysSgQAGp2TdCQAAAA",
    "domain": ".rfihub.com",
    "path": "/",
    "expires": -1,
    "httpOnly": false,
    "secure": true,
    "sameSite": "None"
  },
  {
    "name": "rud",
    "value": "H4sIAAAAAAAA_-MSsjS3MDE3NzExMzAwMzUyMjA1FuIz1E1OjvT1scjOiyysSgQAGp2TdCQAAAA",
    "domain": ".rfihub.com",
    "path": "/",
    "expires": 1795012612.04638,
    "httpOnly": false,
    "secure": true,
    "sameSite": "None"
  },
  {
    "name": "euds",
    "value": "H4sIAAAAAAAA_wXBwRGAMAgEwI_t4BwED2I3xkAhVu7ud8QFjqqV0o4SfxqSzVeidE_utDLcGtShpNoJ5CT9BxHypOI6AAAA",
    "domain": ".rfihub.com",
    "path": "/",
    "expires": -1,
    "httpOnly": false,
    "secure": true,
    "sameSite": "None"
  },
  {
    "name": "TDID",
    "value": "054457a4-f675-4acb-a1fb-783647aa71fd",
    "domain": ".adsrvr.org",
    "path": "/",
    "expires": 1792852612.155725,
    "httpOnly": false,
    "secure": true,
    "sameSite": "None"
  },
  {
    "name": "sd-session-id",
    "value": ".eJwNyksOgyAQANC7zFqaAYbhcxljZUiIShvRTY13r8uXvAvGr-zb1KQdkI79lAHmtT7qkC7o9bfJAgmiD-Q9ESOyMwadhXuALr3XTxtrfopDtiLvoAqhKJoKqlB4Vl50jpyDEYNJe9ZWM2vzQgyRmeD-A5sYJZ0.aPuPBA.guQDHyLxUuCDrQJ4hbB9nPRBrRk",
    "domain": "live.rezync.com",
    "path": "/",
    "expires": 1795012612.147369,
    "httpOnly": true,
    "secure": true,
    "sameSite": "None"
  },
  {
    "name": "TDCPM",
    "value": "CAEYBSABKAIyCwjyz_uOsMXJPhAFOAE.",
    "domain": ".adsrvr.org",
    "path": "/",
    "expires": 1792852612.155808,
    "httpOnly": false,
    "secure": true,
    "sameSite": "None"
  },
  {
    "name": "dsp_4",
    "value": "aa71fd",
    "domain": ".user-sync.fwmrm.net",
    "path": "/",
    "expires": 1766500612.219647,
    "httpOnly": false,
    "secure": true,
    "sameSite": "None"
  },
  {
    "name": "did",
    "value": "s%3Av0%3A0f4bc777-ec65-46af-8c83-7c4a801b9c0c.j00dwp%2BjAvySIhE2YUYS5Y3hzqPIaLrO%2FAqagbxY2sE",
    "domain": "chedraui-prod.us.auth0.com",
    "path": "/",
    "expires": 1792874212.230521,
    "httpOnly": true,
    "secure": true,
    "sameSite": "None"
  },
  {
    "name": "did_compat",
    "value": "s%3Av0%3A0f4bc777-ec65-46af-8c83-7c4a801b9c0c.j00dwp%2BjAvySIhE2YUYS5Y3hzqPIaLrO%2FAqagbxY2sE",
    "domain": "chedraui-prod.us.auth0.com",
    "path": "/",
    "expires": 1792874212.230667,
    "httpOnly": true,
    "secure": true,
    "sameSite": "Lax"
  },
  {
    "name": "rlas3",
    "value": "mRFGwagrFUe6Hs7nNkmi6z0B/Zse+bVf0wmfRtr2FZw=",
    "domain": ".rlcdn.com",
    "path": "/",
    "expires": 1792852612.289407,
    "httpOnly": false,
    "secure": true,
    "sameSite": "None"
  },
  {
    "name": "pxrc",
    "value": "CISe7scGEgUI6AcQABIGCLrqARAA",
    "domain": ".rlcdn.com",
    "path": "/",
    "expires": 1766500612.289567,
    "httpOnly": false,
    "secure": true,
    "sameSite": "None"
  },
  {
    "name": "__rtbh.lid",
    "value": "%7B%22eventType%22%3A%22lid%22%2C%22id%22%3A%22gGp8XCD4fWxHDzkOXbRK%22%2C%22expiryDate%22%3A%222026-10-24T14%3A36%3A53.066Z%22%7D",
    "domain": "chedraui-prod.us.auth0.com",
    "path": "/",
    "expires": 1792852613,
    "httpOnly": false,
    "secure": true,
    "sameSite": "None"
  },
  {
    "name": "smc_ls_session",
    "value": "1761316613365",
    "domain": ".auth0.com",
    "path": "/",
    "expires": -1,
    "httpOnly": false,
    "secure": false,
    "sameSite": "Lax"
  },
  {
    "name": "cto_bundle",
    "value": "YW6DS19JSmVkS0xuMDlvemxhemklMkJvZWdOak96MmszSnFmdUpEJTJGc21PSFloMFpYMHpGYndBWCUyQlhrb1d3WUslMkZwcUR2ZWJYOW1kUmlxSkIxUFE0TjVac0VOdmRYZllIUmJZaU54eVhPWnRoNmgxUnEyRm90TzRNcVU4UURIJTJGZ0RldTlVaVhEeG5xa1JCRnRHUjE1Qld4T1BWdUJRJTNEJTNE",
    "domain": ".criteo.com",
    "path": "/",
    "expires": 1795012612.377561,
    "httpOnly": false,
    "secure": true,
    "sameSite": "None",
    "partitionKey": "https://auth0.com",
    "_crHasCrossSiteAncestor": true
  },
  {
    "name": "cto_bundle",
    "value": "t0M3iF8yZGwlMkJ3aVN5b3VRNk1uR3UlMkJPZjBJUGFXa29ZeFY3bU1TZHRrWjJ1UDAwZWZSa3B6RTlYVGU2azdoVHloSUN1YmdIJTJGQ0JNRkI0ZnRLZEJKYVJub25RSHlpSlg2NGZSYm9ITlE2bERQb2lra3NrYjRhOEt6QnpmYmpFMUZjU09sd0MlMkZXNFZDRXh4ZXlvUzZoalk3ZXFpdyUzRCUzRA",
    "domain": ".auth0.com",
    "path": "/",
    "expires": 1795480613,
    "httpOnly": false,
    "secure": false,
    "sameSite": "Lax"
  },
  {
    "name": "_lr_hb_-zvhuxj%2Ftendaenlinea",
    "value": "{%22heartbeat%22:1761316614129}",
    "domain": "chedraui-prod.us.auth0.com",
    "path": "/",
    "expires": 1761403014,
    "httpOnly": false,
    "secure": false,
    "sameSite": "Lax"
  },
  {
    "name": "_ga_N938TMF9GB",
    "value": "GS2.1.s1761316616$o1$g0$t1761316616$j60$l0$h0",
    "domain": ".auth0.com",
    "path": "/",
    "expires": 1795876616.885979,
    "httpOnly": false,
    "secure": false,
    "sameSite": "Lax"
  },
  {
    "name": "_ga",
    "value": "GA1.1.1369389942.1761316617",
    "domain": ".auth0.com",
    "path": "/",
    "expires": 1795876616.886665,
    "httpOnly": false,
    "secure": false,
    "sameSite": "Lax"
  },
  {
    "name": "_lr_tabs_-zvhuxj%2Ftendaenlinea",
    "value": "{%22recordingID%22:%226-019a16a6-ac6c-76ab-9058-9e875f916cfe%22%2C%22sessionID%22:0%2C%22lastActivity%22:1761316621524%2C%22hasActivity%22:true%2C%22confirmed%22:false%2C%22recordingConditionThreshold%22:32.36165650098351%2C%22clearsIdentifiedUser%22:false}",
    "domain": "chedraui-prod.us.auth0.com",
    "path": "/",
    "expires": 1761403021,
    "httpOnly": false,
    "secure": false,
    "sameSite": "Lax"
  },
  {
    "name": "auth0",
    "value": "s%3Ac977uTGvBHg_JSSDDTU1h5LuzQ2N14Kc.NzS4h98P%2BTohyXzWTnymn7pQPWYtwiwJUmrfeBNSjQQ",
    "domain": "chedraui-prod.us.auth0.com",
    "path": "/",
    "expires": 1762180626.437962,
    "httpOnly": true,
    "secure": true,
    "sameSite": "None"
  },
  {
    "name": "auth0_compat",
    "value": "s%3Ac977uTGvBHg_JSSDDTU1h5LuzQ2N14Kc.NzS4h98P%2BTohyXzWTnymn7pQPWYtwiwJUmrfeBNSjQQ",
    "domain": "chedraui-prod.us.auth0.com",
    "path": "/",
    "expires": 1762180626.438346,
    "httpOnly": true,
    "secure": true,
    "sameSite": "Lax"
  },
  {
    "name": "VtexIdclientAutCookie_chedrauimx",
    "value": "eyJhbGciOiJFUzI1NiIsImtpZCI6IkFBMzQxOUI4QzNBQkY4RDgxOUQ0NTJGN0RGNUIxQ0IzQTZCNkFGQjgiLCJ0eXAiOiJqd3QifQ.eyJzdWIiOiI0ODMwNzhkMS1jYzBiLTQwNzgtYmRlMC1jOWRlY2UyYjg3NWRAbWFpbHNsdXJwLmluZm8iLCJhY2NvdW50IjoiY2hlZHJhdWlteCIsImF1ZGllbmNlIjoid2Vic3RvcmUiLCJleHAiOjE3NjE0MDMwMjcsInR5cGUiOiJ1c2VyIiwidXNlcklkIjoiMWZhYmU5YmEtNjAxOS00NTNjLWI3MGEtMzk1MWZmNDJkYjIzIiwiaWF0IjoxNzYxMzE2NjI3LCJmbGFnIjoib2F1dGhfdnRleGRvbWFpbiIsImlzUmVwcmVzZW50YXRpdmUiOmZhbHNlLCJpc3MiOiJ0b2tlbi1lbWl0dGVyIiwianRpIjoiMDBlZGNlM2UtZDNkNC00Y2Q4LThiM2UtNjczNWY1NTczNWU2In0.I1yI3cMwgg4EZ7hw7rOjFAwFOZJKBLd3bqOgS_q_XqTIbXYkLQ22vWJlu7HnD03cLx_sLxUGsoniTzHsUQIZLg",
    "domain": ".vtexid.vtex.com.br",
    "path": "/",
    "expires": 1761403025.935601,
    "httpOnly": true,
    "secure": true,
    "sameSite": "Lax"
  },
  {
    "name": "VtexIdclientAutCookie_4095fcf9-f929-49a7-a818-8abd1f714a82",
    "value": "eyJhbGciOiJFUzI1NiIsImtpZCI6IkFBMzQxOUI4QzNBQkY4RDgxOUQ0NTJGN0RGNUIxQ0IzQTZCNkFGQjgiLCJ0eXAiOiJqd3QifQ.eyJzdWIiOiI0ODMwNzhkMS1jYzBiLTQwNzgtYmRlMC1jOWRlY2UyYjg3NWRAbWFpbHNsdXJwLmluZm8iLCJhY2NvdW50IjoiY2hlZHJhdWlteCIsImF1ZGllbmNlIjoid2Vic3RvcmUiLCJleHAiOjE3NjE0MDMwMjcsInR5cGUiOiJ1c2VyIiwidXNlcklkIjoiMWZhYmU5YmEtNjAxOS00NTNjLWI3MGEtMzk1MWZmNDJkYjIzIiwiaWF0IjoxNzYxMzE2NjI3LCJmbGFnIjoib2F1dGhfdnRleGRvbWFpbiIsImlzUmVwcmVzZW50YXRpdmUiOmZhbHNlLCJpc3MiOiJ0b2tlbi1lbWl0dGVyIiwianRpIjoiMDBlZGNlM2UtZDNkNC00Y2Q4LThiM2UtNjczNWY1NTczNWU2In0.I1yI3cMwgg4EZ7hw7rOjFAwFOZJKBLd3bqOgS_q_XqTIbXYkLQ22vWJlu7HnD03cLx_sLxUGsoniTzHsUQIZLg",
    "domain": ".vtexid.vtex.com.br",
    "path": "/",
    "expires": 1761403025.935759,
    "httpOnly": true,
    "secure": true,
    "sameSite": "Lax"
  },
  {
    "name": "VtexIdclientAutCookie_chedrauimx",
    "value": "eyJhbGciOiJFUzI1NiIsImtpZCI6IjIyNTU2QkRBMEEwRjdENDE5NTg0RDIyOEIzMDQ1OENENzNGRDQ3NEUiLCJ0eXAiOiJqd3QifQ.eyJzdWIiOiI0ODMwNzhkMS1jYzBiLTQwNzgtYmRlMC1jOWRlY2UyYjg3NWRAbWFpbHNsdXJwLmluZm8iLCJhY2NvdW50IjoiY2hlZHJhdWlteCIsImF1ZGllbmNlIjoid2Vic3RvcmUiLCJzZXNzIjoiYzcyNTI4NjMtYjFkOS00ZjgyLWI5MTctM2I5OGEzZWQ1NmYwIiwiZXhwIjoxNzYxNDAzMDI3LCJ0eXBlIjoidXNlciIsInVzZXJJZCI6IjFmYWJlOWJhLTYwMTktNDUzYy1iNzBhLTM5NTFmZjQyZGIyMyIsImlhdCI6MTc2MTMxNjYyNywiaXNSZXByZXNlbnRhdGl2ZSI6ZmFsc2UsImlzcyI6InRva2VuLWVtaXR0ZXIiLCJqdGkiOiI1YWMwNGNkOS05M2NjLTQzNDktYTRmNS1iOGNiYzFhMGJmZWEifQ.0EZ-a51sKflUGlcYlbgk9SeDXez1CgQLORvfgLlaA4WtGyEkhwpTSPwVg4Z1FVusPUWSo4VLpIsdfl-nTw719g",
    "domain": ".www.chedraui.com.mx",
    "path": "/",
    "expires": 1761403027.023253,
    "httpOnly": true,
    "secure": true,
    "sameSite": "None"
  },
  {
    "name": "VtexIdclientAutCookie_4095fcf9-f929-49a7-a818-8abd1f714a82",
    "value": "eyJhbGciOiJFUzI1NiIsImtpZCI6IjIyNTU2QkRBMEEwRjdENDE5NTg0RDIyOEIzMDQ1OENENzNGRDQ3NEUiLCJ0eXAiOiJqd3QifQ.eyJzdWIiOiI0ODMwNzhkMS1jYzBiLTQwNzgtYmRlMC1jOWRlY2UyYjg3NWRAbWFpbHNsdXJwLmluZm8iLCJhY2NvdW50IjoiY2hlZHJhdWlteCIsImF1ZGllbmNlIjoid2Vic3RvcmUiLCJzZXNzIjoiYzcyNTI4NjMtYjFkOS00ZjgyLWI5MTctM2I5OGEzZWQ1NmYwIiwiZXhwIjoxNzYxNDAzMDI3LCJ0eXBlIjoidXNlciIsInVzZXJJZCI6IjFmYWJlOWJhLTYwMTktNDUzYy1iNzBhLTM5NTFmZjQyZGIyMyIsImlhdCI6MTc2MTMxNjYyNywiaXNSZXByZXNlbnRhdGl2ZSI6ZmFsc2UsImlzcyI6InRva2VuLWVtaXR0ZXIiLCJqdGkiOiI1YWMwNGNkOS05M2NjLTQzNDktYTRmNS1iOGNiYzFhMGJmZWEifQ.0EZ-a51sKflUGlcYlbgk9SeDXez1CgQLORvfgLlaA4WtGyEkhwpTSPwVg4Z1FVusPUWSo4VLpIsdfl-nTw719g",
    "domain": ".www.chedraui.com.mx",
    "path": "/",
    "expires": 1761403027.023288,
    "httpOnly": true,
    "secure": true,
    "sameSite": "None"
  },
  {
    "name": "GRV_5577_ga",
    "value": "GA1.1.903360213.1761316609",
    "domain": ".groovinads.com",
    "path": "/",
    "expires": 1761575827.816808,
    "httpOnly": false,
    "secure": true,
    "sameSite": "None"
  },
  {
    "name": "_TargetOne_Session_Cookie_Time",
    "value": "1761316628433",
    "domain": "www.chedraui.com.mx",
    "path": "/",
    "expires": 1761318428,
    "httpOnly": false,
    "secure": false,
    "sameSite": "Lax"
  },
  {
    "name": "CheckoutOrderFormOwnership",
    "value": "",
    "domain": ".www.chedraui.com.mx",
    "path": "/",
    "expires": 1776868629.674339,
    "httpOnly": true,
    "secure": true,
    "sameSite": "Strict"
  },
  {
    "name": "_lr_tabs_-zvhuxj%2Ftendaenlinea",
    "value": "{%22recordingID%22:%226-019a16a6-9c43-72d6-8eb0-b0d4f423da8a%22%2C%22sessionID%22:0%2C%22lastActivity%22:1761316628947%2C%22hasActivity%22:false%2C%22confirmed%22:false%2C%22recordingConditionThreshold%22:89.92861963277845%2C%22clearsIdentifiedUser%22:false}",
    "domain": "www.chedraui.com.mx",
    "path": "/",
    "expires": 1761403028,
    "httpOnly": false,
    "secure": false,
    "sameSite": "Lax"
  },
  {
    "name": "_lr_hb_-zvhuxj%2Ftendaenlinea",
    "value": "{%22heartbeat%22:1761316628947}",
    "domain": "www.chedraui.com.mx",
    "path": "/",
    "expires": 1761403028,
    "httpOnly": false,
    "secure": false,
    "sameSite": "Lax"
  },
  {
    "name": "AWSALBCORS",
    "value": "WTI9ERxQDZWg7fyxmfxFvEPG8WZH1CTNcGtclWlTxgEvWbc6TxvWDL1KI1CXlfUgDb1SVJg4IBbHw7RS5m41t+TKA/RatfIQ8ie5shrE7oUp6ckTKKzc2XyLhVU3",
    "domain": "widget-mediator.zopim.com",
    "path": "/",
    "expires": 1761921429.621794,
    "httpOnly": false,
    "secure": true,
    "sameSite": "None"
  },
  {
    "name": "_ga_N938TMF9GB",
    "value": "GS2.1.s1761316609$o1$g1$t1761316629$j40$l0$h0",
    "domain": ".chedraui.com.mx",
    "path": "/",
    "expires": 1795876629.983576,
    "httpOnly": false,
    "secure": false,
    "sameSite": "Lax"
  },
  {
    "name": "_uetsid",
    "value": "e05af730b0e611f08d2a19827ce579fb",
    "domain": ".chedraui.com.mx",
    "path": "/",
    "expires": 1761403030,
    "httpOnly": false,
    "secure": false,
    "sameSite": "Lax"
  },
  {
    "name": "_uetvid",
    "value": "e05b1db0b0e611f0824b3520ef063cbf",
    "domain": ".chedraui.com.mx",
    "path": "/",
    "expires": 1795012630,
    "httpOnly": false,
    "secure": false,
    "sameSite": "Lax"
  },
  {
    "name": "vtex_session",
    "value": "eyJhbGciOiJFUzI1NiIsImtpZCI6IjBmMDY3ZDQwLTVhNDAtNGE3ZS1iNjRlLTE3NWZiOWE4ZTExOSIsInR5cCI6IkpXVCJ9.eyJhY2NvdW50LmlkIjpbXSwiaWQiOiJjODEwN2RkOS1lMmZiLTQ4NTYtOTE1NC00Zjc0YTI4MGQ0MzMiLCJ2ZXJzaW9uIjo0LCJzdWIiOiJzZXNzaW9uIiwiYWNjb3VudCI6InNlc3Npb24iLCJleHAiOjE3NjIwMDc4MzAsImlhdCI6MTc2MTMxNjYzMCwianRpIjoiZDI0ODIyODEtYzk1ZC00YmFkLWI2OGMtNDViODc2MTExYjIzIiwiaXNzIjoic2Vzc2lvbi9kYXRhLXNpZ25lciJ9.plHV0dFB4Ck-gGeaFsrKPtVUzzYD2apZHUiQqqhF-mk0hIWYYoIGir0x4HVKElhLR510Kfcz25O75DwGR9-77A",
    "domain": "www.chedraui.com.mx",
    "path": "/",
    "expires": 1761748630.789178,
    "httpOnly": true,
    "secure": true,
    "sameSite": "Lax"
  },
  {
    "name": "vtex_segment",
    "value": "eyJjYW1wYWlnbnMiOm51bGwsImNoYW5uZWwiOiIxIiwicHJpY2VUYWJsZXMiOm51bGwsInJlZ2lvbklkIjoiVTFjalkyaGxaSEpoZFdsdGVEQXdOVGs3WTJobFpISmhkV2x0ZURBMk5qZz0iLCJ1dG1fY2FtcGFpZ24iOm51bGwsInV0bV9zb3VyY2UiOm51bGwsInV0bWlfY2FtcGFpZ24iOm51bGwsImN1cnJlbmN5Q29kZSI6Ik1YTiIsImN1cnJlbmN5U3ltYm9sIjoiJCIsImNvdW50cnlDb2RlIjoiTUVYIiwiY3VsdHVyZUluZm8iOiJlcy1NWCIsImFkbWluX2N1bHR1cmVJbmZvIjoiZXMtTVgiLCJjaGFubmVsUHJpdmFjeSI6InB1YmxpYyIsImZhY2V0cyI6ImNvdW50cnk9TUVYO2Nvb3JkaW5hdGVzPS05OC4yMzk2ODQ5LDE5LjAzODAxNjI7In0",
    "domain": "www.chedraui.com.mx",
    "path": "/",
    "expires": 1761748630.789296,
    "httpOnly": true,
    "secure": true,
    "sameSite": "Lax"
  },
  {
    "name": "ttcsid_C8TOJ8DCSQN3SGB7QUV0",
    "value": "1761316609636::yJ6eVfT20PpxzgnjkUei.1.1761316630849.0",
    "domain": ".chedraui.com.mx",
    "path": "/",
    "expires": 1795012630,
    "httpOnly": false,
    "secure": false,
    "sameSite": "Lax"
  },
  {
    "name": "ttcsid",
    "value": "1761316609638::7fbO_VUZc7sBoWPVfLSz.1.1761316630850.0",
    "domain": ".chedraui.com.mx",
    "path": "/",
    "expires": 1795012630,
    "httpOnly": false,
    "secure": false,
    "sameSite": "Lax"
  },
  {
    "name": "__rtbh.lid",
    "value": "%7B%22eventType%22%3A%22lid%22%2C%22id%22%3A%22Sqzqqk3ppRgc86ks6iJQ%22%2C%22expiryDate%22%3A%222026-10-24T14%3A37%3A11.211Z%22%7D",
    "domain": "www.chedraui.com.mx",
    "path": "/",
    "expires": 1792852631,
    "httpOnly": false,
    "secure": true,
    "sameSite": "None"
  },
  {
    "name": "cto_bundle",
    "value": "alePkV9yN0hhcHVlcmxtQjNwcGZmN1I0MVhzQUptVmlYbkh0WVZXMkJ5bGpRS2s3Qk9QWG5GUE53QUxOJTJCS2U3ckFINmtyckFGZkhlc3RkbGNRUXY5RmY2amJOMG1ZeHU1dmdXVGhLNlZ4aFh2ZmVhdmk0bzMxQzVUR0pvZzJjVnhBZDdLWEc2RXQ0UzVKJTJGdjc3QVloc1pnJTJCekElM0QlM0Q",
    "domain": ".criteo.com",
    "path": "/",
    "expires": 1795012631.441788,
    "httpOnly": false,
    "secure": true,
    "sameSite": "None",
    "partitionKey": "https://chedraui.com.mx",
    "_crHasCrossSiteAncestor": true
  },
  {
    "name": "cto_bundle",
    "value": "li6AtF9JeUhlbm5QbU56aHFBNnclMkZuNlBuZnYzcXRnTjZLJTJCd0FqTTNYMTMwdkd5aThxUGp3SWMlMkZSb2RQY2U0dEI1Y3dDSmZzUDd1Wm1EQXhNamRFV2JoRHYzc3UxWUIySHElMkZjZTRwaUslMkJWR2MlMkJOV3M2OCUyRjRZamY4dkh0em14ZGZxSnRPS1FPc3hhT2ElMkZndUlHVEw2bmQlMkJPNnV1Q2NuYVB3bENCVkp6ME8lMkJnMThCayUzRA",
    "domain": ".chedraui.com.mx",
    "path": "/",
    "expires": 1795480631,
    "httpOnly": false,
    "secure": false,
    "sameSite": "Lax"
  },
  {
    "name": "udmts",
    "value": "1761316631.0",
    "domain": ".udmserve.net",
    "path": "/",
    "expires": 1792852631.762809,
    "httpOnly": false,
    "secure": true,
    "sameSite": "None"
  },
  {
    "name": "dt",
    "value": "F50E3069-8B1F-37A0-8A1C-8A2125D64EC4",
    "domain": ".udmserve.net",
    "path": "/",
    "expires": 1792852631.76292,
    "httpOnly": false,
    "secure": true,
    "sameSite": "None"
  },
  {
    "name": "rtbh",
    "value": "Esa3Q5ccAxG3EFdl0krT_K3pzXkzT1nMPs2PSllGZ9M",
    "domain": ".udmserve.net",
    "path": "/",
    "expires": 1769092631.762965,
    "httpOnly": false,
    "secure": true,
    "sameSite": "None"
  }
]